pydori/BandoriApi.py
pydori/__init__.py
pydori/d_api.py
pydori/loader.py
pydori/p_api.py
pydori/__pycache__/BandoriApi.cpython-38.pyc
pydori/__pycache__/__init__.cpython-38.pyc
pydori/__pycache__/d_api.cpython-38.pyc
pydori/__pycache__/loader.cpython-38.pyc
pydori/__pycache__/p_api.cpython-38.pyc
pydori/models/__init__.py
pydori/models/base.py
pydori/models/gamodels.py
pydori/models/ptymodels.py
pydori/models/__pycache__/__init__.cpython-38.pyc
pydori/models/__pycache__/base.cpython-38.pyc
pydori/models/__pycache__/gamodels.cpython-38.pyc
pydori/models/__pycache__/ptymodels.cpython-38.pyc
pydori-0.5.3.dist-info/LICENSE
pydori-0.5.3.dist-info/METADATA
pydori-0.5.3.dist-info/WHEEL
pydori-0.5.3.dist-info/top_level.txt
pydori-0.5.3.dist-info/RECORD
