Metadata-Version: 2.1
Name: pydori
Version: 0.5.3
Summary: A python wrapper to interact for bandori.party/bandori.ga APIs
Home-page: https://github.com/WiIIiamTang/pydori
Author: William Tang
License: MIT
Keywords: API,Bandori,Bang Dream,rythm game
Platform: UNKNOWN
Classifier: Intended Audience :: Developers
Classifier: Topic :: Software Development :: Build Tools
Classifier: License :: OSI Approved :: MIT License
Classifier: Programming Language :: Python :: 3.6
Classifier: Programming Language :: Python :: 3.7
Classifier: Programming Language :: Python :: 3.8
Classifier: Operating System :: OS Independent
Requires-Dist: requests
